README.md
setup.py
pyfilter/__init__.py
pyfilter/dict_list.py
pyfilter/list.py
pyfilter/tuple_list.py
python_filter.egg-info/PKG-INFO
python_filter.egg-info/SOURCES.txt
python_filter.egg-info/dependency_links.txt
python_filter.egg-info/requires.txt
python_filter.egg-info/top_level.txt