Metadata-Version: 2.1
Name: python-filter
Version: 2.0.6
Summary: A biblioteca python-filter oferece classes eficientes para manipulação de listas em Python, proporcionando operações simples e rápidas para encontrar, filtrar e manipular dados em estruturas de dados comuns.
Author: Marcuth
Author-email: example@gmail.com
License: MIT License
Keywords: filter tools
